{
    "/js/app.js": "/js/app.js",
    "/css/app.css": "/css/app.css",
    "/0.8c235db7f9124df0cb5b.hot-update.js": "/0.8c235db7f9124df0cb5b.hot-update.js",
    "/0.68277550ade8adf2aa87.hot-update.js": "/0.68277550ade8adf2aa87.hot-update.js",
    "/0.764efebd2c9fa7f00868.hot-update.js": "/0.764efebd2c9fa7f00868.hot-update.js",
    "/0.f546afd3bfc1f62c5357.hot-update.js": "/0.f546afd3bfc1f62c5357.hot-update.js",
    "/0.38a30abc527bcc226650.hot-update.js": "/0.38a30abc527bcc226650.hot-update.js",
    "/0.7da46c5637432c142ede.hot-update.js": "/0.7da46c5637432c142ede.hot-update.js"
}
